{
  "questions": [
    {
      "id": 1,
      "question": "自由意志是否真实存在？",
      "category": "形而上学",
      "difficulty": "高",
      "tags": ["自由意志", "决定论", "形而上学"]
    },
    {
      "id": 2,
      "question": "道德是客观存在的还是主观构建的？",
      "category": "伦理学",
      "difficulty": "高",
      "tags": ["元伦理学", "道德实在论", "道德相对主义"]
    },
    {
      "id": 3,
      "question": "意识是否可以被完全还原为大脑的物理过程？",
      "category": "心灵哲学",
      "difficulty": "高",
      "tags": ["心身问题", "物理主义", "二元论"]
    },
    {
      "id": 4,
      "question": "知识是否必须建立在确定性的基础上？",
      "category": "认识论",
      "difficulty": "中",
      "tags": ["知识论", "怀疑论", "基础主义"]
    },
    {
      "id": 5,
      "question": "存在本身是否需要一个定义？",
      "category": "存在论",
      "difficulty": "高",
      "tags": ["存在", "本体论", "形而上学"]
    },
    {
      "id": 6,
      "question": "美是客观存在的还是主观感受？",
      "category": "美学",
      "difficulty": "中",
      "tags": ["美学", "审美判断", "主观主义"]
    },
    {
      "id": 7,
      "question": "语言是否塑造了我们的思维方式？",
      "category": "语言哲学",
      "difficulty": "中",
      "tags": ["语言相对论", "萨丕尔-沃尔夫假说", "认知语言学"]
    },
    {
      "id": 8,
      "question": "科学理论是否能够揭示实在的真相？",
      "category": "科学哲学",
      "difficulty": "高",
      "tags": ["科学实在论", "工具主义", "科学方法"]
    },
    {
      "id": 9,
      "question": "人类行为是自由选择还是被因果律决定的？",
      "category": "行动哲学",
      "difficulty": "高",
      "tags": ["决定论", "自由意志", "行动理论"]
    },
    {
      "id": 10,
      "question": "数学对象是否独立于人类思维存在？",
      "category": "数学哲学",
      "difficulty": "高",
      "tags": ["数学实在论", "形式主义", "直觉主义"]
    }
  ]
}
