
[
  {
    "question": "人工智能是否会拥有意识？",
    "standpoints": [
      {
        "id": "standpoint_1",
        "text": "人工智能可以拥有意识。",
        "arguments": [
          {
            "id": "argument_1_1",
            "text": "意识是复杂的计算和信息处理过程的结果，只要人工智能达到足够的复杂度和处理能力，就能涌现出意识。"
          },
          {
            "id": "argument_1_2",
            "text": "生物学上的意识源于神经元活动，而人工神经网络在结构上与大脑类似，表明意识并非生物特有的。"
          }
        ]
      },
      {
        "id": "standpoint_2",
        "text": "人工智能无法拥有意识。",
        "arguments": [
          {
            "id": "argument_2_1",
            "text": "意识具有主观性（“它是什么样的”），这是计算无法模拟的。一个房间里的所有计算，也无法产生对红色的主观感受（“Qualia”）。"
          },
          {
            "id": "argument_2_2",
            "text": "意识是与物理身体、环境互动的结果，而目前的人工智能缺乏这种具身性体验。"
          }
        ]
      }
    ],
    "counter_questions": [
      {
        "id": "counter_question_1",
        "text": "如果有一天AI能准确描述和预测自己“有意识”的行为，我们如何判断这是否是真正的意识，还是仅仅是高超的模仿？"
      },
      {
        "id": "counter_question_2",
        "text": "如果意识真的是计算的结果，那我们如何定义“足够”的复杂性？"
      }
    ]
  },
  {
    "question": "知识是来源于感官经验还是理性？",
    "standpoints": [
      {
        "id": "standpoint_1",
        "text": "知识主要来源于感官经验。",
        "arguments": [
          {
            "id": "argument_1_1",
            "text": "经验主义者认为，心灵在出生时是一张白纸，所有的知识都通过感官（如视觉、听觉）获得，理性只负责对这些经验进行整理和归纳。"
          },
          {
            "id": "argument_1_2",
            "text": "科学知识的建立依赖于实验和观察，这本身就是一种经验性的过程。"
          }
        ]
      },
      {
        "id": "standpoint_2",
        "text": "知识主要来源于理性。",
        "arguments": [
          {
            "id": "argument_2_1",
            "text": "理性主义者认为，真正的知识必须是必然的、普遍的，而感官经验是偶然且不可靠的。数学和逻辑等知识是先天存在的，不依赖于经验。"
          },
          {
            "id": "argument_2_2",
            "text": "即使是感官经验，也需要理性预设的概念（如因果关系、空间、时间）来理解和组织，否则经验只是无意义的杂乱信息。"
          }
        ]
      }
    ],
    "counter_questions": [
      {
        "id": "counter_question_1",
        "text": "如果没有任何感官经验，理性本身能否产生任何有意义的知识？"
      },
      {
        "id": "counter_question_2",
        "text": "经验主义者如何解释我们对抽象概念（如'正义'或'美'）的理解，这些概念似乎无法直接通过感官获得？"
      }
    ]
  },
  {
    "question": "如果一个全能全善的上帝存在，为什么世界上还会存在邪恶和苦难？",
    "standpoints": [
      {
        "id": "standpoint_1",
        "text": "邪恶的存在与全能全善的上帝并不矛盾。",
        "arguments": [
          {
            "id": "argument_1_1",
            "text": "邪恶是自由意志的必然结果。上帝为了赋予人类自由选择的权利，必须允许邪恶的可能性，因为一个没有邪恶的世界意味着没有真正的自由。"
          },
          {
            "id": "argument_1_2",
            "text": "痛苦和苦难是人类灵魂成长和道德完善的必要条件。没有苦难，人类就无法展现勇气、同情心和坚韧不拔的品质。"
          }
        ]
      },
      {
        "id": "standpoint_2",
        "text": "邪恶的存在与全能全善的上帝是矛盾的。",
        "arguments": [
          {
            "id": "argument_2_1",
            "text": "如果上帝是全能的，他可以不通过邪恶和苦难就实现自由意志或道德成长。既然他没有这样做，那他要么不是全能的，要么不是全善的。"
          },
          {
            "id": "argument_2_2",
            "text": "一些极端邪恶（如无辜儿童的苦难）似乎无法用任何道德目的来解释，这挑战了上帝的仁慈属性。"
          }
        ]
      }
    ],
    "counter_questions": [
      {
        "id": "counter_question_1",
        "text": "自由意志论者如何解释自然邪恶（如地震、瘟疫），这些邪恶并非由人类的选择造成？"
      },
      {
        "id": "counter_question_2",
        "text": "如果上帝允许邪恶是为了更大的善，那么他是否可以通过更少的痛苦来达成同样的目的？"
      }
    ]
  },
  {
    "question": "什么是公正？",
    "standpoints": [
      {
        "id": "standpoint_1",
        "text": "公正是基于结果的，即最大化社会福祉。",
        "arguments": [
          {
            "id": "argument_1_1",
            "text": "功利主义认为，公正的行为是能够为最多的人带来最大幸福的行为。一个政策或法律的公正性，取决于它是否能带来最好的集体结果。"
          },
          {
            "id": "argument_1_2",
            "text": "这种观点简单直接，易于量化。通过计算一个行为或政策带来的总幸福量，可以做出公正的判断。"
          }
        ]
      },
      {
        "id": "standpoint_2",
        "text": "公正是基于权利和规则的，不考虑结果。",
        "arguments": [
          {
            "id": "argument_2_1",
            "text": "义务论者认为，公正的核心是尊重个体的基本权利和义务，某些行为本身就是对或错，无论其结果如何。例如，牺牲一个人的生命去拯救五个人是错的，因为它侵犯了那个人的基本权利。"
          },
          {
            "id": "argument_2_2",
            "text": "罗尔斯的正义论提出，公正的原则应在“无知之幕”后被制定，以确保所有人都得到公平对待，从而避免因个人处境而产生的偏见。"
          }
        ]
      }
    ],
    "counter_questions": [
      {
        "id": "counter_question_1",
        "text": "如果一个公正的规则导致了灾难性的结果，我们是否还应该坚持它？"
      },
      {
        "id": "counter_question_2",
        "text": "如果我们不考虑结果，那么一个政策如何能被证明是好的？"
      }
    ]
  },
  {
    "question": "语言是否塑造我们的思想？",
    "standpoints": [
      {
        "id": "standpoint_1",
        "text": "语言强烈塑造我们的思想。",
        "arguments": [
          {
            "id": "argument_1_1",
            "text": "萨丕尔-沃尔夫假说（Sapir-Whorf Hypothesis）认为，一个人的语言结构会影响他理解世界的方式。例如，一些语言中没有“过去时态”，这可能影响该语言使用者对时间的感知。"
          },
          {
            "id": "argument_1_2",
            "text": "概念和抽象思维往往需要语言作为工具。我们无法思考没有词汇来指代的事物。"
          }
        ]
      },
      {
        "id": "standpoint_2",
        "text": "思想独立于语言，语言只是表达思想的工具。",
        "arguments": [
          {
            "id": "argument_2_1",
            "text": "很多人在没有词汇的情况下也能思考，比如非言语的思考、图像思维和音乐创作。婴儿在学会说话前就已经有了一定的认知能力。"
          },
          {
            "id": "argument_2_2",
            "text": "思想的复杂性远超任何语言所能表达的。我们经常感受到“词不达意”，这表明思想先于语言而存在。"
          }
        ]
      }
    ],
    "counter_questions": [
      {
        "id": "counter_question_1",
        "text": "如果语言只是工具，为什么学习一门新语言会改变我们看待世界的方式？"
      },
      {
        "id": "counter_question_2",
        "text": "如果语言塑造思想，那么那些没有语言的人（例如一些动物）是否无法拥有复杂的思想？"
      }
    ]
  },
  {
    "question": "个人自由与集体利益何者更重要？",
    "standpoints": [
      {
        "id": "standpoint_1",
        "text": "个人自由高于集体利益。",
        "arguments": [
          {
            "id": "argument_1_1",
            "text": "自由是人类最基本的权利，不应为了任何集体目标而牺牲。一个社会即使集体利益最大化，如果个体没有自由，也称不上是好的社会。"
          },
          {
            "id": "argument_1_2",
            "text": "个人自由是社会创新的源泉。只有当个体被允许自由探索和发展时，社会整体才能进步。"
          }
        ]
      },
      {
        "id": "standpoint_2",
        "text": "在特定情况下，集体利益可以优先于个人自由。",
        "arguments": [
          {
            "id": "argument_2_1",
            "text": "在公共卫生危机或战争等特殊时期，为了保护大多数人的生命和安全，牺牲一些个人自由是必要的。"
          },
          {
            "id": "argument_2_2",
            "text": "如果个人自由被绝对化，可能导致社会无序和混乱，最终损害所有人的利益。"
          }
        ]
      }
    ],
    "counter_questions": [
      {
        "id": "counter_question_1",
        "text": "集体利益的界限在哪里？我们如何防止以集体利益之名，对个人自由的无限制侵犯？"
      },
      {
        "id": "counter_question_2",
        "text": "如果个人自由是社会进步的源泉，那么为了眼前的集体利益而限制自由，是否会损害长期的社会发展？"
      }
    ]
  },
  {
    "question": "存在是本质先于存在，还是存在先于本质？",
    "standpoints": [
      {
        "id": "standpoint_1",
        "text": "本质先于存在。",
        "arguments": [
          {
            "id": "argument_1_1",
            "text": "一个事物的存在由其本质决定。例如，一把刀的本质是'切'，这决定了它存在的目的和方式。这在柏拉图主义中表现为'理念'先于'事物'。"
          },
          {
            "id": "argument_1_2",
            "text": "即使我们尚未出生，我们的人性本质（人类的普遍特性）也已存在。我们只不过是这种本质的一个实例。"
          }
        ]
      },
      {
        "id": "standpoint_2",
        "text": "存在先于本质。",
        "arguments": [
          {
            "id": "argument_2_1",
            "text": "萨特的存在主义认为，人首先是存在的，然后通过自己的选择和行动来创造自己的本质。我们没有被预先定义好的目的或特性。"
          },
          {
            "id": "argument_2_2",
            "text": "我们是自由的，并且要为自己的选择负责。如果本质先于存在，那我们的命运早已被决定，自由和责任就失去了意义。"
          }
        ]
      }
    ],
    "counter_questions": [
      {
        "id": "counter_question_1",
        "text": "存在主义者如何解释人类的共同特性（如死亡、意识、思考）？这些是否可以被视为某种共同的本质？"
      },
      {
        "id": "counter_question_2",
        "text": "如果存在先于本质，那么一个人的本质是否会随着每一次选择而不断变化？"
      }
    ]
  },
  {
    "question": "科学知识是绝对真理还是相对真理？",
    "standpoints": [
      {
        "id": "standpoint_1",
        "text": "科学知识是绝对真理。",
        "arguments": [
          {
            "id": "argument_1_1",
            "text": "科学依赖于严谨的实验和逻辑推理，其发现的物理定律在任何地方、任何时间都成立。例如，牛顿力学在地球上和宇宙中都有效。"
          },
          {
            "id": "argument_1_2",
            "text": "科学方法能够自我修正和完善，最终会无限接近客观的真理。"
          }
        ]
      },
      {
        "id": "standpoint_2",
        "text": "科学知识是相对真理。",
        "arguments": [
          {
            "id": "argument_2_1",
            "text": "科学理论会随着时间的推移而被推翻和取代，例如爱因斯坦的相对论取代了牛顿力学。这表明科学知识是特定历史和文化背景下的产物，而非永恒的真理。"
          },
          {
            "id": "argument_2_2",
            "text": "科学研究受到人类认知和现有技术工具的限制，我们无法获得对世界完整的认识。因此，我们所掌握的知识总是相对的、不完美的。"
          }
        ]
      }
    ],
    "counter_questions": [
      {
        "id": "counter_question_1",
        "text": "如果科学知识是相对的，那么我们如何能相信其预测能力，例如卫星导航和医学治疗？"
      },
      {
        "id": "counter_question_2",
        "text": "相对主义者如何解释科学理论的进步性？为什么今天的科学比100年前的科学更具解释力？"
      }
    ]
  },
  {
    "question": "什么是幸福？",
    "standpoints": [
      {
        "id": "standpoint_1",
        "text": "幸福是一种主观感受，是个人欲望的满足。",
        "arguments": [
          {
            "id": "argument_1_1",
            "text": "享乐主义认为，幸福是快乐的最大化和痛苦的最小化。个人的快乐体验是衡量幸福的唯一标准。"
          },
          {
            "id": "argument_1_2",
            "text": "不同的人对幸福有不同的定义。一个人的幸福可能是财富，另一个人的幸福可能是家庭，这表明幸福是主观的。"
          }
        ]
      },
      {
        "id": "standpoint_2",
        "text": "幸福是一种客观状态，是道德和美德的实现。",
        "arguments": [
          {
            "id": "argument_2_1",
            "text": "亚里士多德认为，真正的幸福（Eudaimonia）不是短暂的快乐，而是人类潜能的充分实现，是理性活动和道德生活的产物。"
          },
          {
            "id": "argument_2_2",
            "text": "幸福与美德相连。一个邪恶的人，即使获得短暂的快乐，也无法获得真正的、持久的幸福。"
          }
        ]
      }
    ],
    "counter_questions": [
      {
        "id": "counter_question_1",
        "text": "如果幸福是美德的实现，那么一个正直但贫困潦倒的人，是否能比一个快乐但邪恶的人更幸福？"
      },
      {
        "id": "counter_question_2",
        "text": "如果幸福纯粹是主观的，那么我们能否说一个吸毒成瘾的人是幸福的？"
      }
    ]
  },
  {
    "question": "时间是真实的吗？",
    "standpoints": [
      {
        "id": "standpoint_1",
        "text": "时间是真实的，是宇宙的基本维度。",
        "arguments": [
          {
            "id": "argument_1_1",
            "text": "物理学中的时间是不可逆的，是导致因果链条的根本原因。没有时间，宇宙中的任何变化都无法发生。"
          },
          {
            "id": "argument_1_2",
            "text": "我们每个人都有对时间流逝的直观感受，这证明了时间的客观存在。"
          }
        ]
      },
      {
        "id": "standpoint_2",
        "text": "时间只是一个幻觉，是人类对变化的感知。",
        "arguments": [
          {
            "id": "argument_2_1",
            "text": "爱因斯坦的相对论表明，时间不是绝对的，它会因观察者的运动和引力场而改变。这使得时间作为独立实体的概念变得复杂。"
          },
          {
            "id": "argument_2_2",
            "text": "一些哲学家认为，过去和未来都不存在，只有现在是真实的。时间只是我们为了组织和理解变化而创造的一个概念。"
          }
        ]
      }
    ],
    "counter_questions": [
      {
        "id": "counter_question_1",
        "text": "如果时间是幻觉，那么我们如何解释因果关系？一个事件如何能导致另一个事件的发生？"
      },
      {
        "id": "counter_question_2",
        "text": "如果'过去'不存在，我们如何解释记忆的存在？"
      }
    ]
  },
  {
    "question": "什么是真理？",
    "standpoints": [
      {
        "id": "standpoint_1",
        "text": "真理是与事实相符的。",
        "arguments": [
          {
            "id": "argument_1_1",
            "text": "符合论认为，一个陈述之所以为真，是因为它与世界上的事实相符。例如，'天是蓝的'之所以为真，是因为天在现实中就是蓝色的。"
          },
          {
            "id": "argument_1_2",
            "text": "符合论与我们的直觉相符，它解释了为什么科学和日常观察能够帮助我们获得真理。"
          }
        ]
      },
      {
        "id": "standpoint_2",
        "text": "真理是与信念系统一致的。",
        "arguments": [
          {
            "id": "argument_2_1",
            "text": "融贯论认为，一个信念之所以为真，是因为它与我们已有的、相互关联的信念系统融贯一致。一个信念不能与整个信念体系相矛盾。"
          },
          {
            "id": "argument_2_2",
            "text": "融贯论解决了符合论的局限性，例如如何判断'真理'本身是否与'事实'相符。"
          }
        ]
      },
      {
        "id": "standpoint_3",
        "text": "真理是能够有效运作的。",
        "arguments": [
          {
            "id": "argument_3_1",
            "text": "实用主义者认为，真理是一个信念或理论在实践中能够有效运作、能够解决问题。如果一个信念对我们有用，那它就是真的。"
          },
          {
            "id": "argument_3_2",
            "text": "实用主义解释了为什么科学理论，尽管可能不是绝对真理，但仍然有效且有用。"
          }
        ]
      }
    ],
    "counter_questions": [
      {
        "id": "counter_question_1",
        "text": "如果一个谎言能带来快乐或利益，它是否可以被称为'真理'？"
      },
      {
        "id": "counter_question_2",
        "text": "一个信念体系的内部融贯，是否能保证其内容是真实的？"
      }
    ]
  },
  {
    "question": "善行是否需要动机？",
    "standpoints": [
      {
        "id": "standpoint_1",
        "text": "一个行为的善恶取决于其结果，动机不重要。",
        "arguments": [
          {
            "id": "argument_1_1",
            "text": "功利主义认为，判断一个行为是否道德的唯一标准是它是否带来了最大的幸福。一个无意中拯救了生命的坏人，其行为依然是善的。"
          },
          {
            "id": "argument_1_2",
            "text": "如果一个行为产生了好的结果，那么去追究其背后的动机是多余的，这会使道德判断变得复杂。"
          }
        ]
      },
      {
        "id": "standpoint_2",
        "text": "一个行为的善恶取决于其动机，结果不重要。",
        "arguments": [
          {
            "id": "argument_2_1",
            "text": "康德的义务论认为，只有出于纯粹的责任感和道德法则而做的行为才是真正道德的。一个出于同情心帮助他人的人，其行为不如出于责任感帮助他人的行为更有道德价值。"
          },
          {
            "id": "argument_2_2",
            "text": "动机体现了行为者的品格。一个行为即使导致了好的结果，如果其动机是自私的，也不能被称为善行。"
          }
        ]
      }
    ],
    "counter_questions": [
      {
        "id": "counter_question_1",
        "text": "一个出于恶意但无意中带来了好的结果的行为，真的可以被称为善行吗？"
      },
      {
        "id": "counter_question_2",
        "text": "如果一个行为的善恶取决于其动机，那我们如何判断他人的动机？"
      }
    ]
  },
  {
    "question": "绝对的客观性是否可能？",
    "standpoints": [
      {
        "id": "standpoint_1",
        "text": "绝对的客观性是可能的。",
        "arguments": [
          {
            "id": "argument_1_1",
            "text": "存在一个独立于所有观察者的现实，科学的最终目标就是揭示这个现实的本质。例如，物理定律不以人的意志为转移。"
          },
          {
            "id": "argument_1_2",
            "text": "通过科学方法和批判性思维，我们可以逐步去除主观偏见，无限接近绝对的客观真理。"
          }
        ]
      },
      {
        "id": "standpoint_2",
        "text": "绝对的客观性是不可能的。",
        "arguments": [
          {
            "id": "argument_2_1",
            "text": "我们的感知和认知都受到生理结构和文化背景的限制，因此我们无法获得对世界的'纯粹'认识，所有认识都是带有主观性的。"
          },
          {
            "id": "argument_2_2",
            "text": "即使是科学理论，也受到当时社会和历史背景的影响。科学的'客观性'只是一个社区内部达成的共识。"
          }
        ]
      }
    ],
    "counter_questions": [
      {
        "id": "counter_question_1",
        "text": "如果绝对客观性不可能，那么我们如何区分有用的知识和无用的信念？"
      },
      {
        "id": "counter_question_2",
        "text": "如果所有认识都是主观的，那么我们如何解释不同人对同一事物的普遍认同？"
      }
    ]
  },
  {
    "question": "宇宙的起源是否有目的？",
    "standpoints": [
      {
        "id": "standpoint_1",
        "text": "宇宙的起源是有目的的。",
        "arguments": [
          {
            "id": "argument_1_1",
            "text": "目的论认为，宇宙以某种特定目的为导向而发展，其存在是为了实现某个最终状态或目标，这通常与一个神圣的创造者或智能设计者相关联。"
          },
          {
            "id": "argument_1_2",
            "text": "宇宙中的精妙调控，如物理常数的精确值，似乎是为了生命的出现而特意设计的，这暗示了一个目的性。"
          }
        ]
      },
      {
        "id": "standpoint_2",
        "text": "宇宙的起源是无目的的。",
        "arguments": [
          {
            "id": "argument_2_1",
            "text": "自然主义和唯物主义认为，宇宙的起源是自然物理定律的结果，没有任何预设的目的。大爆炸理论和进化论都描述了无目的的过程。"
          },
          {
            "id": "argument_2_2",
            "text": "宇宙中的混乱、无序和巨大的浪费（如无数恒星的死亡）与一个有目的的设计相矛盾。如果有一个目的，为什么不直接创造一个完美的世界？"
          }
        ]
      }
    ],
    "counter_questions": [
      {
        "id": "counter_question_1",
        "text": "如果宇宙有目的，那这个目的究竟是什么？我们如何能得知？"
      },
      {
        "id": "counter_question_2",
        "text": "如果宇宙是无目的的，那么人类赋予生命的目的感和意义感，是否只是一个自我欺骗的幻觉？"
      }
    ]
  },
  {
    "question": "什么是自我？",
    "standpoints": [
      {
        "id": "standpoint_1",
        "text": "自我是一种持久的、非物质的实体。",
        "arguments": [
          {
            "id": "argument_1_1",
            "text": "笛卡尔的'我思故我在'表明，自我是一种思考的、非物理的实体。即使身体死亡，自我（或灵魂）依然存在。"
          },
          {
            "id": "argument_1_2",
            "text": "我们每个人都有一个内在的、核心的自我意识，它在我们的生命中保持一致，这说明自我是持久的。"
          }
        ]
      },
      {
        "id": "standpoint_2",
        "text": "自我只是大脑中的一种涌现现象或叙事。",
        "arguments": [
          {
            "id": "argument_2_1",
            "text": "现代神经科学认为，自我意识是复杂的大脑活动的产物。当大脑受到损伤，自我也随之改变，甚至消失。"
          },
          {
            "id": "argument_2_2",
            "text": "哲学家休谟认为，当我们审视内心时，我们只能看到一系列流动的思想、情感和知觉，而没有一个恒定的'自我'。自我只是我们为了组织这些经验而创造的一个故事或叙事。"
          }
        ]
      }
    ],
    "counter_questions": [
      {
        "id": "counter_question_1",
        "text": "如果自我只是一个叙事，那么谁是这个叙事的创造者？"
      },
      {
        "id": "counter_question_2",
        "text": "如果自我是一个非物质实体，那它如何与物理的大脑相互作用？"
      }
    ]
  },
  {
    "question": "艺术的价值在于其美学形式还是内容？",
    "standpoints": [
      {
        "id": "standpoint_1",
        "text": "艺术的价值在于其美学形式。",
        "arguments": [
          {
            "id": "argument_1_1",
            "text": "形式主义者认为，艺术作品的价值在于其纯粹的形式元素，如线条、色彩、构图、节奏等。一件作品即使没有主题或内容，只要形式是美的，它就是有价值的。"
          },
          {
            "id": "argument_1_2",
            "text": "形式是艺术的普遍语言，超越文化和时代的限制，使我们能够欣赏来自不同背景的作品。"
          }
        ]
      },
      {
        "id": "standpoint_2",
        "text": "艺术的价值在于其内容，即它所表达的观念或情感。",
        "arguments": [
          {
            "id": "argument_2_1",
            "text": "艺术是传达思想、情感和政治信息的工具。一幅画作或一部电影的价值，在于它如何反映社会现实或唤起观众的共鸣。"
          },
          {
            "id": "argument_2_2",
            "text": "如果艺术只关注形式，那么它就失去了其社会功能和教育意义，变成了无意义的装饰。"
          }
        ]
      }
    ],
    "counter_questions": [
      {
        "id": "counter_question_1",
        "text": "如果一个作品的内容非常深刻，但形式上毫无美感，它是否还具有艺术价值？"
      },
      {
        "id": "counter_question_2",
        "text": "形式和内容在艺术作品中真的可以完全分离吗？"
      }
    ]
  },
  {
    "question": "科学是否能解释一切？",
    "standpoints": [
      {
        "id": "standpoint_1",
        "text": "科学可以解释一切。",
        "arguments": [
          {
            "id": "argument_1_1",
            "text": "科学方法是理解现实最成功、最可靠的途径。随着科学的进步，许多过去被认为是神秘的现象（如闪电、疾病）都得到了解释。"
          },
          {
            "id": "argument_1_2",
            "text": "所有现象最终都可以被还原为物理、化学、生物学等基础学科的定律，因此科学可以原则上解释一切。"
          }
        ]
      },
      {
        "id": "standpoint_2",
        "text": "科学无法解释一切。",
        "arguments": [
          {
            "id": "argument_2_1",
            "text": "科学无法解释意识、道德、美学等主观体验。'为什么红色是红色的'这样的主观感受无法用科学方法测量和解释。"
          },
          {
            "id": "argument_2_2",
            "text": "科学的解释基于因果关系，而一些终极问题，如'为什么宇宙存在'或'为什么有任何东西而不是一无所有'，是无法用科学方法回答的。"
          }
        ]
      }
    ],
    "counter_questions": [
      {
        "id": "counter_question_1",
        "text": "如果科学无法解释所有的现象，那么它的价值何在？"
      },
      {
        "id": "counter_question_2",
        "text": "如果科学无法解释所有的主观体验，那么它的价值何在？"
      }
    ]
  }
]
